cad_to_h5m/__init__.py
cad_to_h5m/core.py
cad_to_h5m-0.3.0.dist-info/LICENSE
cad_to_h5m-0.3.0.dist-info/METADATA
cad_to_h5m-0.3.0.dist-info/WHEEL
cad_to_h5m-0.3.0.dist-info/top_level.txt
cad_to_h5m-0.3.0.dist-info/RECORD
