Metadata-Version: 2.1
Name: cad-to-h5m
Version: 0.3.0
Summary: Converts CAD files to a DAGMC h5m file using Cubit
Home-page: https://github.com/fusion-energy/cad_to_h5m
Author: The cad_to_h5m Development Team
Author-email: mail@jshimwell.com
License: UNKNOWN
Platform: UNKNOWN
Classifier: Natural Language :: English
Classifier: Topic :: Scientific/Engineering
Classifier: Programming Language :: Python :: 3
Classifier: Programming Language :: Python :: 3.6
Classifier: Programming Language :: Python :: 3.7
Classifier: Programming Language :: Python :: 3.8
Classifier: Programming Language :: Python :: 3.9
Classifier: License :: OSI Approved :: MIT License
Classifier: Operating System :: OS Independent
Requires-Python: >=3.6
License-File: LICENSE
